Metadata-Version: 1.0
Name: my-awesome-project
Version: 0.0.1
Summary: Sample project for pip package
Home-page: UNKNOWN
Author: PPG
Author-email: ppg@mail.com
License: UNKNOWN
Platform: UNKNOWN
